Adder_test/CLA_HAN_PG_16.v
/* verilator lint_off UNUSEDSIGNAL */
/* verilator lint_off SELRANGE */
/* verilator lint_off UNOPTFLAT */
module shi_pg_gen_2 (a,b,cin,pp,gnpg,p);

input [16:1]a;
input [16:1]b;
input cin;
output [15:0]pp;
output [15:0]gnpg;
output [16:1]p;
wire [16:1]g;

assign p=a^b;
assign g=a&b;

//level1
wire  [7:0] gnpg_level1;
wire  [7:0] pp_level1;
genvar i;
generate
     for (i = 0;i<8 ;i=i+1 ) begin
        assign gnpg_level1[i]=g[i*2+2]|p[i*2+2]&g[2*i+1];  // gnpg[0]=g2+p2g1
        assign pp_level1[i]=p[i*2+2]&p[i*2+1];              // pp[0]=p2p1
   end
endgenerate

//level2 
wire  [7:0] gnpg_level2;
wire  [7:0] pp_level2;
assign gnpg_level2[0]=gnpg_level1[0];
assign pp_level2[0]=pp_level1[0];


generate
    for (i = 1;i<8 ;i=i+1 ) begin
        assign gnpg_level2[i]=gnpg_level1[i]|pp_level1[i]&gnpg_level1[i-1];  
        assign pp_level2[i]=pp_level1[i]&pp_level1[i-1];
   end
endgenerate

//level3 
wire [7:0] gnpg_level3;
wire [7:0] pp_level3;
assign gnpg_level3[0]=gnpg_level2[0];
assign pp_level3[0]=pp_level2[0];
assign gnpg_level3[1]=gnpg_level2[1];
assign pp_level3[1]=pp_level2[1];

generate
    for (i = 2;i<8 ;i=i+1 ) begin
        assign gnpg_level3[i]=gnpg_level2[i]|pp_level2[i]&gnpg_level2[i-2]; 
        assign pp_level3[i]=pp_level2[i]&pp_level2[i-2];
   end
endgenerate
// level 4
wire [3:0] gnpg_level4;
wire [3:0] pp_level4;

generate
    for (i = 0;i<4 ;i=i+1 ) begin
        assign gnpg_level4[i]= gnpg_level3[i+4]|pp_level3[i+4]&gnpg_level3[i];
        assign pp_level4[i]= pp_level3[i+4]&pp_level3[i];
   end
endgenerate
//level 5 for every bit

assign gnpg[0]=g[1];
assign pp[0]=p[1];
assign gnpg[1]=gnpg_level1[0];
assign pp[1]=pp_level1[0];

assign gnpg[2]= g[3]|p[3]&gnpg[1];
assign pp[2]= p[3]&pp[1];
assign gnpg[3]= gnpg_level3[1];
assign pp[3]= pp_level3[1];
assign gnpg[4]= g[5]|p[5]&gnpg[3];
assign pp[4]= p[5]&pp[3];

assign gnpg[5]= gnpg_level3[2];
assign pp[5]= pp_level3[2];
assign gnpg[6]= g[7]|p[7]&gnpg[5];
assign pp[6]= p[7]&pp[5];

assign gnpg[7]= gnpg_level3[3];
assign pp[7]= pp_level3[3];
assign gnpg[8]= g[9]|p[9]&gnpg[7];
assign pp[8]= p[9]&pp[7];

assign gnpg[9]= gnpg_level4[0];
assign pp[9]= pp_level4[0];
assign gnpg[10]= g[11]|p[11]&gnpg[9];
assign pp[10]= p[11]&pp[9];

assign gnpg[11]= gnpg_level4[1];
assign pp[11]= pp_level4[1];
assign gnpg[12]= g[13]|p[13]&gnpg[11];
assign pp[12]= p[13]&pp[11];

assign gnpg[13]= gnpg_level4[2];
assign pp[13]= pp_level4[2];
assign gnpg[14]= g[15]|p[15]&gnpg[13];
assign pp[14]= p[15]&pp[13];

assign gnpg[15]= gnpg_level4[3];
assign pp[15]= pp_level4[3];

endmodule

module CLA_HAN_PG_16 (a,b,cin,sum,cout);
input [16:1]a;
input [16:1]b;
input cin;
output [16:1]sum;
output cout;
wire [16:1]p;
wire [15:0]gnpg;
wire [15:0]c;
wire [15:0]pp;

shi_pg_gen_2 u0 (a,b,cin,pp,gnpg,p);
assign c[0]=cin;
assign c[1]=gnpg[0]|pp[0]&cin;
assign c[2]=gnpg[1]|pp[1]&cin;
assign c[3]=gnpg[2]|pp[2]&cin;
assign c[4]=gnpg[3]|pp[3]&cin;
assign c[5]=gnpg[4]|pp[4]&cin;
assign c[6]=gnpg[5]|pp[5]&cin;
assign c[7]=gnpg[6]|pp[6]&cin;
assign c[8]=gnpg[7]|pp[7]&cin;
assign c[9]=gnpg[8]|pp[8]&cin;
assign c[10]=gnpg[9]|pp[9]&cin;
assign c[11]=gnpg[10]|pp[10]&cin;
assign c[12]=gnpg[11]|pp[11]&cin;
assign c[13]=gnpg[12]|pp[12]&cin;
assign c[14]=gnpg[13]|pp[13]&cin;
assign c[15]=gnpg[14]|pp[14]&cin;

assign cout=gnpg[15]|pp[15]&cin;

assign sum[1]=p[1]^c[0];
assign sum[16:2]=p[16:2]^c[15:1];
endmodule

Adder_test/tb_bka.v
module tb_bka_16 (
    
);
reg [15:0] a,b;
output [15:0] sum;
output  cout;
reg cin;
parameter delay=20; 

CLA_HAN_PG_16 shi (a,b,cin,sum,cout);

initial begin
   $dumpfile("dump.vcd"); 
   $dumpvars;
end


initial begin                                                  
#10   a=2;b=5;cin=1'b0;             
#delay a=1;b=1;
#delay a=20;b=20;cin=1;
#delay a=75;b=75;cin=1;
#delay a=128;b=128;cin=0;
#delay a=200;b=20;cin=0;   
#delay a=2000;b=2000;cin=0;   
#delay a=6500;b=2000;cin=0;   
#delay a=65000;b=200;cin=1;


end 
// initial begin
//   clk=0;
//      forever #10 clk = ~clk;  
// end 


initial begin 
    #1000 $finish;
end


endmodule //tb_c_select_adder_8

Adder_test/dump.vcd
$date
	Sat May 20 00:43:25 2023
$end
$version
	Icarus Verilog
$end
$timescale
	1s
$end
$scope module tb_bka_16 $end
$var wire 16 ! sum [15:0] $end
$var wire 1 " cout $end
$var reg 16 # a [15:0] $end
$var reg 16 $ b [15:0] $end
$var reg 1 % cin $end
$scope module shi $end
$var wire 16 & a [16:1] $end
$var wire 16 ' b [16:1] $end
$var wire 1 % cin $end
$var wire 1 " cout $end
$var wire 16 ( sum [16:1] $end
$var wire 16 ) pp [15:0] $end
$var wire 16 * p [16:1] $end
$var wire 16 + gnpg [15:0] $end
$var wire 16 , c [15:0] $end
$scope module u0 $end
$var wire 16 - a [16:1] $end
$var wire 16 . b [16:1] $end
$var wire 1 % cin $end
$var wire 16 / g [16:1] $end
$var wire 16 0 p [16:1] $end
$var wire 4 1 pp_level4 [3:0] $end
$var wire 8 2 pp_level3 [7:0] $end
$var wire 8 3 pp_level2 [7:0] $end
$var wire 8 4 pp_level1 [7:0] $end
$var wire 16 5 pp [15:0] $end
$var wire 4 6 gnpg_level4 [3:0] $end
$var wire 8 7 gnpg_level3 [7:0] $end
$var wire 8 8 gnpg_level2 [7:0] $end
$var wire 8 9 gnpg_level1 [7:0] $end
$var wire 16 : gnpg [15:0] $end
$scope begin genblk1[0] $end
$upscope $end
$scope begin genblk1[1] $end
$upscope $end
$scope begin genblk1[2] $end
$upscope $end
$scope begin genblk1[3] $end
$upscope $end
$scope begin genblk1[4] $end
$upscope $end
$scope begin genblk1[5] $end
$upscope $end
$scope begin genblk1[6] $end
$upscope $end
$scope begin genblk1[7] $end
$upscope $end
$scope begin genblk2[1] $end
$upscope $end
$scope begin genblk2[2] $end
$upscope $end
$scope begin genblk2[3] $end
$upscope $end
$scope begin genblk2[4] $end
$upscope $end
$scope begin genblk2[5] $end
$upscope $end
$scope begin genblk2[6] $end
$upscope $end
$scope begin genblk2[7] $end
$upscope $end
$scope begin genblk3[2] $end
$upscope $end
$scope begin genblk3[3] $end
$upscope $end
$scope begin genblk3[4] $end
$upscope $end
$scope begin genblk3[5] $end
$upscope $end
$scope begin genblk3[6] $end
$upscope $end
$scope begin genblk3[7] $end
$upscope $end
$scope begin genblk4[0] $end
$upscope $end
$scope begin genblk4[1] $end
$upscope $end
$scope begin genblk4[2] $end
$upscope $end
$scope begin genblk4[3] $end
$upscope $end
$upscope $end
$upscope $end
$upscope $end
$enddefinitions $end
#0
$dumpvars
bx :
bx 9
bx 8
bx 7
bx 6
bx 5
bx 4
bx 3
bx 2
bx 1
bx 0
bx /
bx .
bx -
bx ,
bx +
bx *
bx )
bx (
bx '
bx &
x%
bx $
bx #
x"
bx !
$end
#10
0"
b0 6
b0 1
b1 2
b0 7
b1 3
b0 8
b1 4
b0 9
b111 !
b111 (
b111 )
b111 5
b0 +
b0 :
b111 *
b111 0
b0 /
b0 ,
0%
b101 $
b101 '
b101 .
b10 #
b10 &
b10 -
#30
b0 2
b0 3
b10 ,
b0 4
b10 !
b10 (
b0 )
b0 5
b1 +
b1 :
b0 *
b0 0
b1 /
b1 $
b1 '
b1 .
b1 #
b1 &
b1 -
#50
b101001 !
b101001 (
b10100 +
b10100 :
b10100 /
b101001 ,
1%
b10100 $
b10100 '
b10100 .
b10100 #
b10100 &
b10100 -
#70
b10010111 !
b10010111 (
b11 7
b11 8
b10010111 ,
b11 9
b1001011 +
b1001011 :
b1001011 /
b1001011 $
b1001011 '
b1001011 .
b1001011 #
b1001011 &
b1001011 -
#90
b1000 7
b1000 8
b1000 9
b100000000 !
b100000000 (
b10000000 +
b10000000 :
b10000000 /
b100000000 ,
0%
b10000000 $
b10000000 '
b10000000 .
b10000000 #
b10000000 &
b10000000 -
#110
b0 ,
b0 +
b0 :
b0 7
b0 8
b1010 4
b11011100 !
b11011100 (
b0 9
b11011100 *
b11011100 0
b0 /
b10100 $
b10100 '
b10100 .
b11001000 #
b11001000 &
b11001000 -
#130
b1 6
b11000 7
b11000 8
b111110100000 ,
b0 4
b111110100000 !
b111110100000 (
b11000 9
b11111010000 +
b11111010000 :
b0 *
b0 0
b11111010000 /
b11111010000 $
b11111010000 '
b11111010000 .
b11111010000 #
b11111010000 &
b11111010000 -
#150
b11 6
b111000 7
b111000 8
b11111110000000 ,
b100100 4
b10000100110100 !
b10000100110100 (
b11000 9
b1111111000000 +
b1111111000000 :
b1111010110100 *
b1111010110100 0
b101000000 /
b1100101100100 #
b1100101100100 &
b1100101100100 -
#170
0"
b0 6
b1010 7
b11000000 3
b1010 8
b11100000 4
b1010 9
b111001000 +
b111001000 :
b1111111010110001 !
b1111111010110001 (
b1111110100100000 *
b1111110100100000 0
b11001000 /
b1110010001 ,
1%
b11001000 $
b11001000 '
b11001000 .
b1111110111101000 #
b1111110111101000 &
b1111110111101000 -
