SRT_Divider/on_the_fly_conversion_srt4.sv
`define INTWIDTH 32 // A tmp value, should be changed depending on the design spec
`define POS_two  3'b010
`define NEG_two  3'b110
`define POS_one  3'b001
`define NEG_one  3'b111
`define POS_zero 3'b000

module Int_fast_convert (quotient_radix_4, clk,rst, result);
input logic [2:0] quotient_radix_4; 
output logic [`INTWIDTH-1:0] result;

input logic clk,rst;
logic [`INTWIDTH-1:0] Q_pos,Q_neg;
logic [`INTWIDTH-1:0] Q_pos_next ,Q_neg_next;


// using truth table to avoid adder implementation
// assign Q_pos_next= ~quotient_radix_4[2]?{Q_pos[`INTWIDTH-3:0],quotient_radix_4[1:0]}:{Q_neg[`INTWIDTH-3:0],quotient_radix_4[1:0]};
// assign Q_neg_next=(~quotient_radix_4[2]&(quotient_radix_4[1]^quotient_radix_4[0]))?
//                                                             {Q_pos[`INTWIDTH-3:0],quotient_radix_4[2:1]}:
//                                                             {Q_neg[`INTWIDTH-3:0],~(quotient_radix_4[1]^quotient_radix_4[0]),~quotient_radix_4[0]};
always_comb begin
    if (quotient_radix_4 == `POS_two || 
        quotient_radix_4 == `NEG_two || 
        quotient_radix_4 == `POS_one || 
        quotient_radix_4 == `NEG_one || 
        quotient_radix_4 == `POS_zero) begin
        // 你的原始逻辑
        Q_pos_next = ~quotient_radix_4[2] ? {Q_pos[`INTWIDTH-3:0], quotient_radix_4[1:0]} : {Q_neg[`INTWIDTH-3:0], quotient_radix_4[1:0]};
        Q_neg_next = (~quotient_radix_4[2] & (quotient_radix_4[1] ^ quotient_radix_4[0])) ? {Q_pos[`INTWIDTH-3:0], quotient_radix_4[2:1]} : {Q_neg[`INTWIDTH-3:0], ~(quotient_radix_4[1] ^ quotient_radix_4[0]), ~quotient_radix_4[0]};
    end else begin
        Q_pos_next = 0;
        Q_neg_next = 0;
    end
end


always_ff @(posedge clk or negedge rst)begin
if (~rst)begin
    Q_pos<=0;
    Q_neg<=0;
end
else begin
    Q_pos<=Q_pos_next;
    Q_neg<=Q_neg_next;
end

end

assign result=Q_pos;





endmodule

SRT_Divider/tb_ontfc.sv
`include "on_the_fly_conversion_srt4.sv"

module otfc_tb;

logic [2:0] quotient_radix_4; 
logic [`INTWIDTH-1:0] result;
logic clk,rst;

Int_fast_convert otfc(quotient_radix_4, clk,rst, result);
// 时钟生成器
always begin
    #5 clk = ~clk;
end
initial begin
   $dumpfile("dump.vcd"); 
   $dumpvars(0, otfc); // 0表示记录所有层次，wal_mul_tb是模块的实例名
end

// 测试向量生成
initial begin
    clk = 0;
    rst=0;
    #50 rst=1;
    #5 quotient_radix_4=2;
    #10 quotient_radix_4=1;
    #10 quotient_radix_4=0;
    #10 quotient_radix_4=-2;
    #10 quotient_radix_4=-1;
    #100;
    $finish;
end



endmodule

SRT_Divider/dump.vcd
$date
	Tue Oct 24 17:24:12 2023
$end

$version
	Synopsys VCS version Q-2020.03-SP1_Full64
$end

$timescale
	1s
$end

$comment Csum: 1 bb38ae5d9185b0f4 $end


$scope module otfc_tb $end

$scope module otfc $end
$var reg 3 ! quotient_radix_4 [2:0] $end
$var reg 32 " result [31:0] $end
$var reg 1 # clk $end
$var reg 1 $ rst $end
$var reg 32 % Q_pos [31:0] $end
$var reg 32 & Q_neg [31:0] $end
$var reg 32 ' Q_pos_next [31:0] $end
$var reg 32 ( Q_neg_next [31:0] $end
$upscope $end

$upscope $end

$enddefinitions $end

#0
$dumpvars
b00000000000000000000000000000000 &
b00000000000000000000000000000000 (
b00000000000000000000000000000000 %
b00000000000000000000000000000000 '
bxxx !
b00000000000000000000000000000000 "
0#
0$
$end
#5
1#
#10
0#
#15
1#
#20
0#
#25
1#
#30
0#
#35
1#
#40
0#
#45
1#
#50
1$
0#
#55
b010 !
1#
b00000000000000000000000000000010 '
b00000000000000000000000000000001 (
b00000000000000000000000000000010 %
b00000000000000000000000000000010 "
b00000000000000000000000000000001 &
b00000000000000000000000000001010 '
b00000000000000000000000000001001 (
#60
0#
#65
b001 !
1#
b00000000000000000000000000001001 '
b00000000000000000000000000001000 (
b00000000000000000000000000001001 %
b00000000000000000000000000001001 "
b00000000000000000000000000001000 &
b00000000000000000000000000100101 '
b00000000000000000000000000100100 (
#70
0#
#75
b000 !
1#
b00000000000000000000000000100100 '
b00000000000000000000000000100011 (
b00000000000000000000000000100100 %
b00000000000000000000000000100100 "
b00000000000000000000000000100011 &
b00000000000000000000000010010000 '
b00000000000000000000000010001111 (
#80
0#
#85
b110 !
1#
b00000000000000000000000010001110 '
b00000000000000000000000010001101 (
b00000000000000000000000010001110 %
b00000000000000000000000010001110 "
b00000000000000000000000010001101 &
b00000000000000000000001000110110 '
b00000000000000000000001000110101 (
#90
0#
#95
b111 !
1#
b00000000000000000000001000110111 '
b00000000000000000000001000110110 (
b00000000000000000000001000110111 %
b00000000000000000000001000110111 "
b00000000000000000000001000110110 &
b00000000000000000000100011011011 '
b00000000000000000000100011011010 (
#100
0#
#105
1#
b00000000000000000000100011011011 %
b00000000000000000000100011011011 "
b00000000000000000000100011011010 &
b00000000000000000010001101101011 '
b00000000000000000010001101101010 (
#110
0#
#115
1#
b00000000000000000010001101101011 %
b00000000000000000010001101101011 "
b00000000000000000010001101101010 &
b00000000000000001000110110101011 '
b00000000000000001000110110101010 (
#120
0#
#125
1#
b00000000000000001000110110101011 %
b00000000000000001000110110101011 "
b00000000000000001000110110101010 &
b00000000000000100011011010101011 '
b00000000000000100011011010101010 (
#130
0#
#135
1#
b00000000000000100011011010101011 %
b00000000000000100011011010101011 "
b00000000000000100011011010101010 &
b00000000000010001101101010101011 '
b00000000000010001101101010101010 (
#140
0#
#145
1#
b00000000000010001101101010101011 %
b00000000000010001101101010101011 "
b00000000000010001101101010101010 &
b00000000001000110110101010101011 '
b00000000001000110110101010101010 (
#150
0#
#155
1#
b00000000001000110110101010101011 %
b00000000001000110110101010101011 "
b00000000001000110110101010101010 &
b00000000100011011010101010101011 '
b00000000100011011010101010101010 (
#160
0#
#165
1#
b00000000100011011010101010101011 %
b00000000100011011010101010101011 "
b00000000100011011010101010101010 &
b00000010001101101010101010101011 '
b00000010001101101010101010101010 (
#170
0#
#175
1#
b00000010001101101010101010101011 %
b00000010001101101010101010101011 "
b00000010001101101010101010101010 &
b00001000110110101010101010101011 '
b00001000110110101010101010101010 (
#180
0#
#185
1#
b00001000110110101010101010101011 %
b00001000110110101010101010101011 "
b00001000110110101010101010101010 &
b00100011011010101010101010101011 '
b00100011011010101010101010101010 (
