basic_circuits/tb_CLAv2_8bit.v
module tb_CLAv2_8bit (
    
);

reg [15:0] a,b;
wire [15:0] sum;
wire  cout;

reg cin;
parameter delay=20; 
CLA_16_bit_block cla (a,b,cin,sum,cout);


initial begin
   $dumpfile("dump.vcd"); 
   $dumpvars;
end


initial begin                                                  
#10   a=2;b=5;cin=1'b0;             
#delay a=1;b=1;
#delay a=20;b=20;cin=1;
#delay a=75;b=75;cin=1;
#delay a=128;b=128;cin=0;
#delay a=200;b=20;cin=0;      
#delay a=1024;b=1024;cin=0;
#delay a=2048;b=2048;cin=0;
#delay a=4096;b=4096;cin=0;
#delay a=8192;b=8192;cin=0;
#delay a=16384;b=16384;cin=0;         
#delay a=2000;b=2230;cin=0;                                                                                 

end 

// initial begin
//   clk=0;
//      forever #10 clk = ~clk;  
// end 


initial begin 
    #1000 $finish;
end








endmodule //tb_CLAv2_8bit

basic_circuits/CLA_block.v
module CLA_4_bit_block(a,b,cin,sum,cout);
input [3:0] a,b;
input cin;
output [3:0] sum;
output cout;
wire [3:0] p,g,c;
pg_gen_4 u0 (a,b,p,g);
assign c[0]=cin;
assign c[1]= g[0]|(p[0]&cin);
assign c[2]= g[1]|(p[1]& g[0]|(p[0]&cin));
assign c[3]= g[2]|(p[2]& (g[1]|(p[1]& g[0]|(p[0]&cin))));
assign cout= g[3]|(p[3]& (g[2]|(p[2]& (g[1]|(p[1]& g[0]|(p[0]&cin))))));
assign sum = p^c;
endmodule

module pg_gen_4 (
    a,b,p,g    
);
input [3:0]a,b;
output [3:0]p,g;

assign p=a^b;
assign g=a&b;

endmodule 

module CLA_8_bit_block(a,b,cin,sum,cout);
input [7:0] a,b;
input cin;
output [7:0] sum;
output cout;
wire [7:0] p,g,c;
pg_gen_8 u0 (a,b,p,g);
assign c[0]=cin;
assign c[1]= g[0]|(p[0]&cin);
assign c[2]= g[1]|(p[1]& g[0]|(p[0]&cin));
assign c[3]= g[2]|(p[2]& g[1]|(p[1]& g[0]|(p[0]&cin)));
assign c[4]= g[3]|(p[3]&g[2]|(p[2]& g[1]|(p[1]& g[0]|(p[0]&cin))));
assign c[5]= g[4]|(p[4]&g[3]|(p[3]&g[2]|(p[2]& g[1]|(p[1]& g[0]|(p[0]&cin)))));
assign c[6]= g[5]|(p[5]&g[4]|(p[4]&g[3]|(p[3]&g[2]|(p[2]& g[1]|(p[1]& g[0]|(p[0]&cin))))));
assign c[7]= g[6]|(p[6]&g[5]|(p[5]&g[4]|(p[4]&g[3]|(p[3]&g[2]|(p[2]& g[1]|(p[1]& g[0]|(p[0]&cin)))))));
assign cout= g[7]|(p[7]&g[6]|(p[6]&g[5]|(p[5]&g[4]|(p[4]&g[3]|(p[3]&g[2]|(p[2]& g[1]|(p[1]& g[0]|(p[0]&cin))))))));
assign sum=p^c;
endmodule

module pg_gen_8 (
    a,b,p,g    
);
input [7:0]a,b;
output [7:0]p,g;
assign p=a^b;
assign g=a&b;
endmodule 

module CLA_16_bit_block(a,b,cin,sum,cout);
input [15:0] a,b;
input cin;
output [15:0] sum;
output cout;
wire [15:0] p,g,c;
pg_gen_16 u0 (a,b,p,g);
assign c[0]=cin;
assign c[1]= g[0]|(p[0]&cin);
assign c[2]= g[1]|(p[1]& (g[0]|(p[0]&cin)));
assign c[3]= g[2]|(p[2]& (g[1]|(p[1]& (g[0]|(p[0]&cin)))));
assign c[4]= g[3]|(p[3]& (g[2]|(p[2]& (g[1]|(p[1]& (g[0]|(p[0]&cin)))))) );
assign c[5]= g[4]|(p[4]& (g[3]|(p[3]& (g[2]|(p[2]& (g[1]|(p[1]& (g[0]|(p[0]&cin)))))) )));
assign c[6]= g[5]|(p[5]& (g[4]|(p[4]& (g[3]|(p[3]& (g[2]|(p[2]& (g[1]|(p[1]& (g[0]|(p[0]&cin)))))) )))));
assign c[7]= g[6]|(p[6]& (g[5]|(p[5]& (g[4]|(p[4]& (g[3]|(p[3]& (g[2]|(p[2]& (g[1]|(p[1]& (g[0]|(p[0]&cin)))))) )))))));
assign c[8]= g[7]|(p[7]& (g[6]|(p[6]& (g[5]|(p[5]& (g[4]|(p[4]& (g[3]|(p[3]& (g[2]|(p[2]& (g[1]|(p[1]& (g[0]|(p[0]&cin)))))) )))))))));
assign c[9]= g[8]|(p[8]& (g[7]|(p[7]& (g[6]|(p[6]& (g[5]|(p[5]& (g[4]|(p[4]& (g[3]|(p[3]& (g[2]|(p[2]& (g[1]|(p[1]& (g[0]|(p[0]&cin)))))) )))))))))));
assign c[10]= g[9]|(p[9]& (g[8]|(p[8]& (g[7]|(p[7]& (g[6]|(p[6]& (g[5]|(p[5]& (g[4]|(p[4]& (g[3]|(p[3]& (g[2]|(p[2]& (g[1]|(p[1]& (g[0]|(p[0]&cin)))))) )))))))))))));
assign c[11]= g[10]|(p[10]& (g[9]|(p[9]& (g[8]|(p[8]& (g[7]|(p[7]& (g[6]|(p[6]& (g[5]|(p[5]& (g[4]|(p[4]& (g[3]|(p[3]& (g[2]|(p[2]& (g[1]|(p[1]& (g[0]|(p[0]&cin)))))) )))))))))))))));
assign c[12]= g[11]|(p[11]& ( g[10]|(p[10]& (g[9]|(p[9]& (g[8]|(p[8]& (g[7]|(p[7]& (g[6]|(p[6]& (g[5]|(p[5]& (g[4]|(p[4]& (g[3]|(p[3]& (g[2]|(p[2]& (g[1]|(p[1]& (g[0]|(p[0]&cin)))))) )))))))))))))))));
assign c[13]= g[12]|(p[12]& ( g[11]|(p[11]& ( g[10]|(p[10]& (g[9]|(p[9]& (g[8]|(p[8]& (g[7]|(p[7]& (g[6]|(p[6]& (g[5]|(p[5]& (g[4]|(p[4]& (g[3]|(p[3]& (g[2]|(p[2]& (g[1]|(p[1]& (g[0]|(p[0]&cin)))))) )))))))))))))))))));
assign c[14]= g[13]|(p[13]& (g[12]|(p[12]& ( g[11]|(p[11]& ( g[10]|(p[10]& (g[9]|(p[9]& (g[8]|(p[8]& (g[7]|(p[7]& (g[6]|(p[6]& (g[5]|(p[5]& (g[4]|(p[4]& (g[3]|(p[3]& (g[2]|(p[2]& (g[1]|(p[1]& (g[0]|(p[0]&cin)))))) )))))))))))))))))))));
assign c[15]= g[14]|(p[14]& (g[13]|(p[13]& (g[12]|(p[12]& ( g[11]|(p[11]& ( g[10]|(p[10]& (g[9]|(p[9]& (g[8]|(p[8]& (g[7]|(p[7]& (g[6]|(p[6]& (g[5]|(p[5]& (g[4]|(p[4]& (g[3]|(p[3]& (g[2]|(p[2]& (g[1]|(p[1]& (g[0]|(p[0]&cin)))))) )))))))))))))))))))))));
assign cout= g[15]|(p[15]& (g[14]|(p[14]& (g[13]|(p[13]& (g[12]|(p[12]& ( g[11]|(p[11]& ( g[10]|(p[10]& (g[9]|(p[9]& (g[8]|(p[8]& (g[7]|(p[7]& (g[6]|(p[6]& (g[5]|(p[5]& (g[4]|(p[4]& (g[3]|(p[3]& (g[2]|(p[2]& (g[1]|(p[1]& (g[0]|(p[0]&cin)))))) )))))))))))))))))))))))));

// assign c[0]=cin;
// assign c[15:1]=g[14:0]|(p[14:0]&c[14:0]); // 62 bits
// assign cout = g[15]|(p[15]&c[15]); //cin 63th bit

assign sum=p^c;
endmodule

module pg_gen_16 (
    a,b,p,g    
);
input [15:0]a,b;
output [15:0]p,g;
assign p=a^b;
assign g=a&b;
endmodule 

module CLA_32_bit_block(a,b,cin,sum,cout);
input [31:0] a,b;
input cin;
output [31:0] sum;
output cout;
wire [31:0] p,g,c;
pg_gen_32 u0 (a,b,p,g);
assign c[0]=cin;
assign c[31:1]=g[30:0]|(p[30:0]&c[30:0]); // 62 bits
assign cout = g[31]|(p[31]&c[31]); //cin 63th bit
assign sum[0]=p[0]^c[0];
assign sum[31:1]=p[31:1]^c[31:1];
endmodule

module pg_gen_32 (
    a,b,p,g    
);
input [31:0]a,b;
output [31:0]p,g;
assign p=a^b;
assign g=a&b;
endmodule

basic_circuits/dump.vcd
$date
	Wed Mar 15 18:09:08 2023
$end
$version
	Icarus Verilog
$end
$timescale
	1s
$end
$scope module CLA_32_bit_block $end
$var wire 32 ! a [31:0] $end
$var wire 32 " b [31:0] $end
$var wire 1 # cin $end
$var wire 1 $ cout $end
$var wire 32 % sum [31:0] $end
$var wire 32 & p [31:0] $end
$var wire 32 ' g [31:0] $end
$var wire 32 ( c [31:0] $end
$scope module u0 $end
$var wire 32 ) a [31:0] $end
$var wire 32 * b [31:0] $end
$var wire 32 + g [31:0] $end
$var wire 32 , p [31:0] $end
$upscope $end
$upscope $end
$scope module CLA_4_bit_block $end
$var wire 4 - a [3:0] $end
$var wire 4 . b [3:0] $end
$var wire 1 / cin $end
$var wire 1 0 cout $end
$var wire 4 1 sum [3:0] $end
$var wire 4 2 p [3:0] $end
$var wire 4 3 g [3:0] $end
$var wire 4 4 c [3:0] $end
$scope module u0 $end
$var wire 4 5 a [3:0] $end
$var wire 4 6 b [3:0] $end
$var wire 4 7 g [3:0] $end
$var wire 4 8 p [3:0] $end
$upscope $end
$upscope $end
$scope module CLA_8_bit_block $end
$var wire 8 9 a [7:0] $end
$var wire 8 : b [7:0] $end
$var wire 1 ; cin $end
$var wire 1 < cout $end
$var wire 8 = sum [7:0] $end
$var wire 8 > p [7:0] $end
$var wire 8 ? g [7:0] $end
$var wire 8 @ c [7:0] $end
$scope module u0 $end
$var wire 8 A a [7:0] $end
$var wire 8 B b [7:0] $end
$var wire 8 C g [7:0] $end
$var wire 8 D p [7:0] $end
$upscope $end
$upscope $end
$scope module tb_CLAv2_8bit $end
$var wire 16 E sum [15:0] $end
$var wire 1 F cout $end
$var reg 16 G a [15:0] $end
$var reg 16 H b [15:0] $end
$var reg 1 I cin $end
$scope module cla $end
$var wire 16 J a [15:0] $end
$var wire 16 K b [15:0] $end
$var wire 1 I cin $end
$var wire 1 F cout $end
$var wire 16 L sum [15:0] $end
$var wire 16 M p [15:0] $end
$var wire 16 N g [15:0] $end
$var wire 16 O c [15:0] $end
$scope module u0 $end
$var wire 16 P a [15:0] $end
$var wire 16 Q b [15:0] $end
$var wire 16 R g [15:0] $end
$var wire 16 S p [15:0] $end
$upscope $end
$upscope $end
$upscope $end
$enddefinitions $end
#0
$dumpvars
bx S
bx R
bx Q
bx P
bx O
bx N
bx M
bx L
bx K
bx J
xI
bx H
bx G
xF
bx E
bx D
bx C
bz B
bz A
bxz @
bx ?
bx >
bx =
x<
z;
bz :
bz 9
bx 8
bx 7
bz 6
bz 5
bxz 4
bx 3
bx 2
bx 1
x0
z/
bz .
bz -
bx ,
bx +
bz *
bz )
bxz (
bx '
bx &
bx %
x$
z#
bz "
bz !
$end
#10
0F
b111 E
b111 L
b111 M
b111 S
b0 N
b0 R
b0 O
0I
b101 H
b101 K
b101 Q
b10 G
b10 J
b10 P
#30
b10 O
b10 E
b10 L
b0 M
b0 S
b1 N
b1 R
b1 H
b1 K
b1 Q
b1 G
b1 J
b1 P
#50
b101001 E
b101001 L
b10100 N
b10100 R
b101001 O
1I
b10100 H
b10100 K
b10100 Q
b10100 G
b10100 J
b10100 P
#70
b10010111 E
b10010111 L
b10010111 O
b1001011 N
b1001011 R
b1001011 H
b1001011 K
b1001011 Q
b1001011 G
b1001011 J
b1001011 P
#90
b100000000 E
b100000000 L
b10000000 N
b10000000 R
b100000000 O
0I
b10000000 H
b10000000 K
b10000000 Q
b10000000 G
b10000000 J
b10000000 P
#110
b0 O
b11011100 E
b11011100 L
b11011100 M
b11011100 S
b0 N
b0 R
b10100 H
b10100 K
b10100 Q
b11001000 G
b11001000 J
b11001000 P
#130
b100000000000 O
b100000000000 E
b100000000000 L
b0 M
b0 S
b10000000000 N
b10000000000 R
b10000000000 H
b10000000000 K
b10000000000 Q
b10000000000 G
b10000000000 J
b10000000000 P
#150
b1000000000000 E
b1000000000000 L
b1000000000000 O
b100000000000 N
b100000000000 R
b100000000000 H
b100000000000 K
b100000000000 Q
b100000000000 G
b100000000000 J
b100000000000 P
#170
b10000000000000 E
b10000000000000 L
b10000000000000 O
b1000000000000 N
b1000000000000 R
b1000000000000 H
b1000000000000 K
b1000000000000 Q
b1000000000000 G
b1000000000000 J
b1000000000000 P
#190
b100000000000000 E
b100000000000000 L
b100000000000000 O
b10000000000000 N
b10000000000000 R
b10000000000000 H
b10000000000000 K
b10000000000000 Q
b10000000000000 G
b10000000000000 J
b10000000000000 P
#210
b1000000000000000 E
b1000000000000000 L
b1000000000000000 O
b100000000000000 N
b100000000000000 R
b100000000000000 H
b100000000000000 K
b100000000000000 Q
b100000000000000 G
b100000000000000 J
b100000000000000 P
#230
b1111111100000 O
b1000010000110 E
b1000010000110 L
b111101100110 M
b111101100110 S
b10010000 N
b10010000 R
b100010110110 H
b100010110110 K
b100010110110 Q
b11111010000 G
b11111010000 J
b11111010000 P
